compat.py
ftpretty.py
ftpretty-0.4.0.dist-info/AUTHORS.rst
ftpretty-0.4.0.dist-info/LICENSE.txt
ftpretty-0.4.0.dist-info/METADATA
ftpretty-0.4.0.dist-info/WHEEL
ftpretty-0.4.0.dist-info/top_level.txt
ftpretty-0.4.0.dist-info/RECORD
