Metadata-Version: 1.1
Name: ftpretty
Version: 0.4.0
Summary: Pretty FTP wrapper
Home-page: https://github.com/codebynumbers/ftpretty/
Author: Rob Harrigan
Author-email: harrigan.rob@gmail.com
License: MIT
Download-URL: https://github.com/codebynumbers/ftpretty/tarball/0.4.0
Platform: UNKNOWN
Classifier: Topic :: Internet :: File Transfer Protocol (FTP)
Classifier: Topic :: Utilities
Classifier: Development Status :: 4 - Beta
Classifier: License :: OSI Approved :: MIT License
Classifier: Operating System :: OS Independent
Classifier: Programming Language :: Python
Classifier: Programming Language :: Python :: 2
Classifier: Programming Language :: Python :: 2.7
Classifier: Programming Language :: Python :: 3
Classifier: Programming Language :: Python :: 3.5
Classifier: Programming Language :: Python :: 3.6
Classifier: Programming Language :: Python :: 3.7
Classifier: Programming Language :: Python :: 3.8
Classifier: Programming Language :: Python :: 3.9
Classifier: Intended Audience :: Developers
Classifier: Intended Audience :: System Administrators
